LICENSE.txt
README.md
setup.py
Rooz/__init__.py
Rooz.egg-info/PKG-INFO
Rooz.egg-info/SOURCES.txt
Rooz.egg-info/dependency_links.txt
Rooz.egg-info/top_level.txt