Metadata-Version: 2.1
Name: Rooz
Version: 0.9.3
Summary: By This Lib You Can DownLoad From Social Media
Author: Ali-Mahmoud-Fadhil
Classifier: Programming Language :: Python :: 3
Classifier: Operating System :: OS Independent
Classifier: License :: OSI Approved :: MIT License
License-File: LICENSE.txt
